monte_carlo_analysis/__init__.py
monte_carlo_analysis/settings.py
monte_carlo_analysis/analysis/Analysis.py
monte_carlo_analysis/analysis/MelbaAnalysis.py
monte_carlo_analysis/analysis/MelbaDiceAnalysis.py
monte_carlo_analysis/analysis/MelbaDistributionAnalysis.py
monte_carlo_analysis/analysis/__init__.py
monte_carlo_analysis/metrics/AUCPRClassWiseMetric.py
monte_carlo_analysis/metrics/AUCPRMetric.py
monte_carlo_analysis/metrics/AUCROCMetric.py
monte_carlo_analysis/metrics/BRATSMetric.py
monte_carlo_analysis/metrics/Metric.py
monte_carlo_analysis/metrics/__init__.py
monte_carlo_analysis/strategies/AverageSingleDistributionStrategy.py
monte_carlo_analysis/strategies/ClassWiseDistributionStrategy.py
monte_carlo_analysis/strategies/ClassWiseStrategy.py
monte_carlo_analysis/strategies/MultipleDistributionsStrategy.py
monte_carlo_analysis/strategies/OneVersusAllStrategy.py
monte_carlo_analysis/strategies/Strategy.py
monte_carlo_analysis/strategies/TopDistributionsSimilarityStrategy.py
monte_carlo_analysis/strategies/TopSingleDistributionStrategy.py
monte_carlo_analysis/strategies/__init__.py
monte_carlo_analysis/uncertainty_metrics/BhattacharyaCoefficentDistributionSimilarity.py
monte_carlo_analysis/uncertainty_metrics/DistributionSimilarityUncertaintyMetric.py
monte_carlo_analysis/uncertainty_metrics/EarthMoverDistanceDistributionSimilarity.py
monte_carlo_analysis/uncertainty_metrics/EntropyMultipleDistributions.py
monte_carlo_analysis/uncertainty_metrics/EntropySingleDistribution.py
monte_carlo_analysis/uncertainty_metrics/KullbackLeiblerDivergenceDistributionSimilarity.py
monte_carlo_analysis/uncertainty_metrics/MultipleDistributionsUncertaintyMetric.py
monte_carlo_analysis/uncertainty_metrics/MutualInformationMultipleDistribution.py
monte_carlo_analysis/uncertainty_metrics/SingleDistributionUncertaintyMetric.py
monte_carlo_analysis/uncertainty_metrics/UncertaintyMetric.py
monte_carlo_analysis/uncertainty_metrics/VarianceSingleDistribution.py
monte_carlo_analysis-0.0.1.dist-info/LICENSE
monte_carlo_analysis-0.0.1.dist-info/METADATA
monte_carlo_analysis-0.0.1.dist-info/WHEEL
monte_carlo_analysis-0.0.1.dist-info/top_level.txt
monte_carlo_analysis-0.0.1.dist-info/RECORD
