Metadata-Version: 2.1
Name: monte-carlo-analysis
Version: 0.0.1
Summary: Package that analyses the output of a monte-carlo dropout network
Home-page: UNKNOWN
Author: Robin Camarasa
Author-email: r.camarasa@erasmusmc.nl
License: UNKNOWN
Platform: UNKNOWN
Requires-Dist: numpy
Requires-Dist: pytest
Requires-Dist: joblib
Requires-Dist: tox
Requires-Dist: numba
Requires-Dist: sklearn
Requires-Dist: pandas
Requires-Dist: matplotlib
Requires-Dist: seaborn
